myabcm_corporate_client_api/__init__.py
myabcm_corporate_client_api/corporate_server_module.py
myabcm_corporate_client_api-0.2.1.dist-info/licenses/LICENSE
myabcm_corporate_client_api-0.2.1.dist-info/METADATA
myabcm_corporate_client_api-0.2.1.dist-info/WHEEL
myabcm_corporate_client_api-0.2.1.dist-info/top_level.txt
myabcm_corporate_client_api-0.2.1.dist-info/RECORD
