Metadata-Version: 2.4
Name: myabcm_corporate_client_api
Version: 0.2.1
Summary: MyABCM Corporate Python Client API
Author-email: Luiz Guilherme Oliveira <luiz.oliveira@myabcm.com>, Clovis Ribeiro <clovis.ribeiro@myabcm.com>
License: LGPL-3.0-only
Project-URL: Homepage, https://www.myabcm.com
Project-URL: Repository, https://github.com/myabcm/corporate-python-client-api
Classifier: Programming Language :: Python :: 3
Classifier: Operating System :: OS Independent
Classifier: License :: OSI Approved :: GNU Lesser General Public License v3 (LGPLv3)
Requires-Python: >=3.12
License-File: LICENSE
Requires-Dist: requests
Dynamic: license-file
